<?xml version="1.0" encoding="UTF-8" standalone="yes"?>

<item>
<title>-[COLOR red] Narcos[/COLOR]</title>
<link>http://Ignoreme</link>
<thumbnail>http://ayayay.tv/wp-content/uploads/2015/10/narcos.jpg</thumbnail>
<fanart>http://www.queveoennetflix.com/wp-content/uploads/2015/10/narcos-larga.png</fanart>
<externallink>https://raw.githubusercontent.com/lokiyotnt69/general/master/narcos.xml</externallink>	
</item>

<item>
<title>-[COLOR red] Scandal[/COLOR]</title>
<link>http://Ignoreme</link>
<thumbnail></thumbnail>
<fanart></fanart>
<externallink>https://raw.githubusercontent.com/lokiyotnt69/Series/master/scandal.xml</externallink>	
</item>    


<item>
<title>-[COLOR red] Walking dead [/COLOR]</title>
<link>http://Ignoreme</link>
<thumbnail></thumbnail>
<fanart></fanart>
<externallink></externallink>	
</item> 
    
		
	







<hannel>
<name>[COLOR red]J[/COLOR][COLOR blue]H[/COLOR][COLOR red]G[/COLOR] ** The Walking Dead temporada 1  **</name>
<thumbnail></thumbnail>
<fanart></fanart>
<items>

<item>
<title>[COLOR red]J[/COLOR][COLOR blue]H[/COLOR][COLOR red]G[/COLOR] ** 01 **</title>
<urlsolve>http://streamin.to/u5yon0g4vnwh</urlsolve>
<thumbnail></thumbnail>
<fanart></fanart>
</item>



